README.md
setup.py
foxrestapiclient/__init__.py
foxrestapiclient.egg-info/PKG-INFO
foxrestapiclient.egg-info/SOURCES.txt
foxrestapiclient.egg-info/dependency_links.txt
foxrestapiclient.egg-info/requires.txt
foxrestapiclient.egg-info/top_level.txt
foxrestapiclient/connection/__init__.py
foxrestapiclient/connection/const.py
foxrestapiclient/connection/rest_api_client.py
foxrestapiclient/connection/rest_api_responses.py
foxrestapiclient/devices/__init__.py
foxrestapiclient/devices/const.py
foxrestapiclient/devices/fox_base_device.py
foxrestapiclient/devices/fox_dim1s2_device.py
foxrestapiclient/devices/fox_dimmable_device.py
foxrestapiclient/devices/fox_led2s2_device.py
foxrestapiclient/devices/fox_r1s1_device.py
foxrestapiclient/devices/fox_r2s2_device.py
foxrestapiclient/devices/fox_rgbw_device.py
foxrestapiclient/devices/fox_service_discovery.py
foxrestapiclient/devices/fox_str1s2_device.py
test/__init__.py
test/const.py
test/test_DIM1S2Device.py
test/test_DimmableDevice.py
test/test_FoxBaseDevice.py
test/test_LED2S2Device.py
test/test_R1S1Device.py
test/test_R2S2Device.py
test/test_RGBWDevice.py
test/test_RestApiClient.py
test/test_STR1S2Device.py
test/test_ServiceDiscovery.py