Metadata-Version: 2.1
Name: foxrestapiclient
Version: 0.1.12
Summary: Connect to F&F Fox devices via RestAPI.
Home-page: https://github.com/fandf92/foxrestapiclient
Author: F&F Filipowski Sp. j.
Author-email: t.waclawiak@fif.com.pl
License: MIT
Platform: UNKNOWN
